Tests/__init__.py
Tests/tests.py
file/__init__.py
file/calculator.py
TACalculator_v4-0.2.dist-info/LICENSE
TACalculator_v4-0.2.dist-info/METADATA
TACalculator_v4-0.2.dist-info/WHEEL
TACalculator_v4-0.2.dist-info/top_level.txt
TACalculator_v4-0.2.dist-info/RECORD
